CODE_OF_CONDUCT.md
README.md
requirements.txt
kover/__init__.py
kover/bulk_write_builder.py
kover/client.py
kover/codes.py
kover/collection.py
kover/cursor.py
kover/database.py
kover/enums.py
kover/exceptions.py
kover/helpers.py
kover/py.typed
kover/schema.py
kover/session.py
kover/transaction.py
kover/typings.py
kover/uri_parser.py
kover/_internals/__init__.py
kover/_internals/_mixins.py
kover/_internals/_serializers.py
kover/bson/__init__.py
kover/bson/_helpers.py
kover/bson/binary.py
kover/bson/code.py
kover/bson/codec_options.py
kover/bson/datetime_ms.py
kover/bson/dbref.py
kover/bson/decimal128.py
kover/bson/errors.py
kover/bson/int64.py
kover/bson/json_util.py
kover/bson/max_key.py
kover/bson/min_key.py
kover/bson/objectid.py
kover/bson/raw_bson.py
kover/bson/regex.py
kover/bson/son.py
kover/bson/timestamp.py
kover/bson/typings.py
kover/bson/tz_util.py
kover/gridfs/__init__.py
kover/gridfs/exceptions.py
kover/gridfs/gridfs.py
kover/gridfs/models.py
kover/metadata/__init__.py
kover/metadata/definitions.py
kover/models/__init__.py
kover/models/operations.py
kover/models/other.py
kover/models/replset.py
kover/network/__init__.py
kover/network/auth.py
kover/network/compressors.py
kover/network/resolver.py
kover/network/transport.py
kover/network/wirehelper.py
kover-2.7.3.dist-info/METADATA
kover-2.7.3.dist-info/WHEEL
kover-2.7.3.dist-info/licenses/LICENSE
kover-2.7.3.dist-info/RECORD
