Metadata-Version: 2.4
Name: kover
Version: 2.7.3
Summary: Fully async mongodb driver for mongod and replica sets.
Project-URL: Repository, https://github.com/megawattka/kover
Project-URL: Documentation, https://github.com/megawattka/kover
Author-email: megawattka <gunter56741@gmail.com>
License-Expression: MIT
License-File: LICENSE
Keywords: async driver,kover,kover mongodb,mongo async,mongod driver,mongodb
Classifier: Development Status :: 4 - Beta
Classifier: Intended Audience :: Developers
Classifier: License :: OSI Approved :: MIT License
Classifier: Operating System :: OS Independent
Classifier: Programming Language :: Python :: 3 :: Only
Classifier: Programming Language :: Python :: 3.10
Classifier: Topic :: Database
Classifier: Topic :: Software Development :: Libraries :: Python Modules
Classifier: Topic :: Software Development :: Quality Assurance
Classifier: Typing :: Typed
Requires-Python: >=3.10
Requires-Dist: dnspython>=2.7.0
Requires-Dist: pydantic>=2.10.6
Requires-Dist: typing-extensions>=4.12.2
Provides-Extra: snappy
Requires-Dist: python-snappy; extra == 'snappy'
Provides-Extra: zstd
Requires-Dist: zstd; extra == 'zstd'
